past/Evaluation.py
past/Loss.py
past/Model.py
past/Modules.py
past/Utils.py
past/__init__.py
bio_past-1.6.0.dist-info/LICENSE
bio_past-1.6.0.dist-info/METADATA
bio_past-1.6.0.dist-info/WHEEL
bio_past-1.6.0.dist-info/top_level.txt
bio_past-1.6.0.dist-info/RECORD
