Metadata-Version: 2.1
Name: bio-past
Version: 1.6.0
Summary: PAST: latent feature extraction with a Prior-based self-Attention framework for Spatial Transcriptomics
Home-page: https://github.com/lizhen18THU/PAST
Author: Zhen Li
Author-email: lizhen18THU@163.com
License: MIT License
Keywords: pip,past
Platform: UNKNOWN
Classifier: Intended Audience :: Science/Research
Classifier: License :: OSI Approved :: MIT License
Classifier: Programming Language :: Python :: 3.8
Classifier: Operating System :: MacOS :: MacOS X
Classifier: Operating System :: Microsoft :: Windows
Classifier: Operating System :: POSIX :: Linux
Classifier: Topic :: Scientific/Engineering :: Bio-Informatics
Requires-Python: >3.6.0
License-File: LICENSE
Requires-Dist: numba (>=0.55.1)
Requires-Dist: numpy (>=1.21.5)
Requires-Dist: pandas (>=1.3.4)
Requires-Dist: scipy (>=1.5.3)
Requires-Dist: scikit-learn (>=1.0.2)
Requires-Dist: scanpy (>=1.9.1)
Requires-Dist: torch (>=1.9.1)
